biomed_enriched/__init__.py
biomed_enriched/_enricher.py
biomed_enriched/_extractor.py
biomed_enriched/_mapper.py
biomed_enriched/cli.py
biomed_enriched-0.1.0.dist-info/LICENSE
biomed_enriched-0.1.0.dist-info/METADATA
biomed_enriched-0.1.0.dist-info/WHEEL
biomed_enriched-0.1.0.dist-info/entry_points.txt
biomed_enriched-0.1.0.dist-info/RECORD
