Metadata-Version: 2.3
Name: biomed-enriched
Version: 0.1.0
Summary: Populate text paragraphs into PubMed sample datasets using a pre-built PMC XML index.
License: MIT
Keywords: pubmed,biomedical,nlp,datasets,huggingface
Author: rian-t
Author-email: rian.touchent@inria.fr
Requires-Python: >=3.10
Classifier: Development Status :: 4 - Beta
Classifier: Intended Audience :: Science/Research
Classifier: License :: OSI Approved :: MIT License
Classifier: Programming Language :: Python :: 3
Classifier: Programming Language :: Python :: 3 :: Only
Classifier: Programming Language :: Python :: 3.9
Classifier: Programming Language :: Python :: 3.10
Classifier: Topic :: Scientific/Engineering :: Bio-Informatics
Provides-Extra: maintainer
Requires-Dist: datasets (>=3.6.0,<4.0.0)
Requires-Dist: huggingface-hub (>=0.21.4,<1.0.0) ; extra == "maintainer"
Requires-Dist: lxml (>=5.4.0,<6.0.0)
Requires-Dist: pandas (>=2.3.0,<3.0.0) ; extra == "maintainer"
Requires-Dist: typer[all] (>=0.9.0,<1.0.0)
